.gitignore
.pre-commit-config.yaml
LICENSE
README.md
environment.yml
mkdocs.yml
pyproject.toml
.github/ISSUE_TEMPLATE/bug-report.yml
.github/ISSUE_TEMPLATE/feature-request.yml
.github/workflows/gh-pages.yml
.github/workflows/lint.yml
.github/workflows/pypi_release.yml
.github/workflows/tests.yml
PyDMConverter.egg-info/PKG-INFO
PyDMConverter.egg-info/SOURCES.txt
PyDMConverter.egg-info/dependency_links.txt
PyDMConverter.egg-info/entry_points.txt
PyDMConverter.egg-info/requires.txt
PyDMConverter.egg-info/top_level.txt
app/resources/file_minus.png
app/resources/file_plus.png
app/resources/file_x.png
app/resources/folder_plus.png
app/resources/folder_search.png
app/resources/play_circle_outline.png
app/resources/settings.png
app/src/model/__init__.py
app/src/model/app_model.py
app/src/model/options_model.py
app/src/view/__init__.py
app/src/view/file_select_widget.py
app/src/view/main_window.py
app/src/view/main_window.ui
app/src/view/options_window.py
app/src/view/output_select_dialog.py
docs/arguments.md
docs/index.md
docs/user_guide.md
docs/images/pydmconverter.png
docs/reference/custom_types.md
docs/reference/index.md
docs/reference/pydm-converter-tool.md
docs/reference/widgets.md
docs/reference/widgets_helpers.md
docs/reference/edm/converter.md
docs/reference/edm/converter_helpers.md
docs/reference/edm/menumux.md
docs/reference/edm/parser.md
docs/reference/edm/parser_helpers.md
examples/TEM_mapping.edl
examples/all_bsy0_main.edl
examples/all_bsy0_main_with_groups.edl
examples/prosilica.edl
pydmconverter/__init__.py
pydmconverter/__main__.py
pydmconverter/custom_types.py
pydmconverter/launch_gui.sh
pydmconverter/widgets.py
pydmconverter/widgets_helpers.py
pydmconverter/edm/__init__.py
pydmconverter/edm/converter.py
pydmconverter/edm/converter_helpers.py
pydmconverter/edm/menumux.py
pydmconverter/edm/parser.py
pydmconverter/edm/parser_helpers.py
tests/__init__.py
tests/test_main.py
tests/test_widgets.py
tests/test_widgets_helpers.py
tests/edm/test_converter.py
tests/edm/test_converter_helpers.py
tests/edm/test_parser.py
tests/edm/test_parser_helpers.py