Metadata-Version: 2.4
Name: PyDMConverter
Version: 1.0.2
Summary: converter to generate pydm .ui files from other display managers.
Author: Devan Agrawal, Zach Domke, Ryan McClanahan, Alexander Ng, Logan Somoza, Alexandria Ikuma
Author-email: Yekta Yazar <yazar@slac.stanford.edu>
License:                     GNU GENERAL PUBLIC LICENSE
Project-URL: Homepage, https://github.com/slaclab/pydm-converter-tool
Project-URL: Bug Tracker, https://github.com/slaclab/pydm-converter-tool/issues
Keywords: PyDM,converter,GUI
Classifier: Development Status :: 4 - Beta
Classifier: License :: OSI Approved :: GNU General Public License (GPL)
Classifier: Natural Language :: English
Classifier: Programming Language :: Python :: 3 :: Only
Classifier: Programming Language :: Python :: 3.12
Classifier: Intended Audience :: Science/Research
Classifier: Topic :: Scientific/Engineering
Requires-Python: >=3.10
License-File: LICENSE
Requires-Dist: pydm
Requires-Dist: pyqt5
Provides-Extra: dev
Requires-Dist: pytest; extra == "dev"
Requires-Dist: pytest-cov; extra == "dev"
Requires-Dist: pytest-qt; extra == "dev"
Requires-Dist: pytest-mock; extra == "dev"
Dynamic: license-file
